setup.py
inverness/__init__.py
inverness/model.py
inverness/model_ann.py
inverness/model_dictionary.py
inverness/model_lsi.py
inverness/model_meta.py
inverness/model_params.py
inverness/model_phraser.py
inverness/model_sentencer.py
inverness/model_subword.py
inverness/model_tfidf.py
inverness/sorbet.py
inverness/util_config.py
inverness/util_coverage.py
inverness/util_time.py
inverness.egg-info/PKG-INFO
inverness.egg-info/SOURCES.txt
inverness.egg-info/dependency_links.txt
inverness.egg-info/requires.txt
inverness.egg-info/top_level.txt