Metadata-Version: 1.1
Name: inverness
Version: 0.1.2
Summary: Natural Language Processing framework built on top of gensim and nmslib.
Home-page: UNKNOWN
Author: Maciej Obarski
Author-email: mobarski@gmail.com
License: UNKNOWN
Keywords: NLP
Platform: UNKNOWN
Classifier: License :: OSI Approved :: MIT License
